mcp_excel/__init__.py
mcp_excel/main.py
mcp_excel-0.1.2.dist-info/METADATA
mcp_excel-0.1.2.dist-info/WHEEL
mcp_excel-0.1.2.dist-info/entry_points.txt
mcp_excel-0.1.2.dist-info/licenses/LICENSE
mcp_excel-0.1.2.dist-info/RECORD
