Metadata-Version: 2.4
Name: mcp-excel
Version: 0.1.2
Summary: MCP server to give client the ability to read Excel files
Project-URL: Homepage, https://github.com/ericjulianto/mcp-excel
Project-URL: Repository, https://github.com/ericjulianto/mcp-excel.git
License-File: LICENSE
Requires-Python: >=3.12
Requires-Dist: mcp[cli]>=1.3.0
Requires-Dist: openpyxl>=3.1.5
Requires-Dist: pandas>=2.2.3
Requires-Dist: py>=1.11.0
